pychime/__init__.py
pychime-0.2.0.dist-info/DESCRIPTION.rst
pychime-0.2.0.dist-info/METADATA
pychime-0.2.0.dist-info/RECORD
pychime-0.2.0.dist-info/WHEEL
pychime-0.2.0.dist-info/metadata.json
pychime-0.2.0.dist-info/top_level.txt
