Metadata-Version: 2.0
Name: pychime
Version: 0.2.0
Summary: A library to use Amazon Chime Web Hooks
Home-page: https://github.com/ozgurakan/pychime
Author: Oz Akan
Author-email: code@akan.me
License: UNKNOWN
Keywords: rss,feed,aws,dynamodb
Platform: UNKNOWN
Requires-Python: >=3
Requires-Dist: requests
